{
  "unversionedId": "scalars/currency",
  "id": "scalars/currency",
  "isDocsHomePage": false,
  "title": "Currency",
  "description": "A field whose value is an ISO-4217 currency.",
  "source": "@site/docs/scalars/currency.md",
  "slug": "/scalars/currency",
  "permalink": "/docs/scalars/currency",
  "editUrl": "https://github.com/urigo/graphql-scalars/edit/master/website/docs/scalars/currency.md",
  "version": "current",
  "sidebar_label": "Currency",
  "sidebar": "sidebar",
  "previous": {
    "title": "Byte",
    "permalink": "/docs/scalars/byte"
  },
  "next": {
    "title": "DateTime",
    "permalink": "/docs/scalars/date-time"
  }
}
